_libjpeg.cp37-win_amd64.pyd
libjpeg/__init__.py
libjpeg/_libjpeg.cpp
libjpeg/_libjpeg.pyx
libjpeg/_version.py
libjpeg/utils.py
libjpeg/src/interface/decode.cpp
libjpeg/src/interface/decode.hpp
libjpeg/src/interface/streamhook.cpp
libjpeg/src/interface/streamhook.hpp
libjpeg/src/interface/utils.hpp
libjpeg/src/libjpeg/.git
libjpeg/src/libjpeg/.gitignore
libjpeg/src/libjpeg/Makefile
libjpeg/src/libjpeg/Makefile.template
libjpeg/src/libjpeg/Makefile_Settings.clang
libjpeg/src/libjpeg/Makefile_Settings.gcc
libjpeg/src/libjpeg/README
libjpeg/src/libjpeg/README.history
libjpeg/src/libjpeg/README.license.gpl
libjpeg/src/libjpeg/README.license.itu
libjpeg/src/libjpeg/README.md
libjpeg/src/libjpeg/autoconfig.h.in
libjpeg/src/libjpeg/automakefile.in
libjpeg/src/libjpeg/config.h
libjpeg/src/libjpeg/configure
libjpeg/src/libjpeg/configure.in
libjpeg/src/libjpeg/cptosvn
libjpeg/src/libjpeg/cutheader.pl
libjpeg/src/libjpeg/doxyconfig
libjpeg/src/libjpeg/doxyfilter.py
libjpeg/src/libjpeg/newheader
libjpeg/src/libjpeg/boxes/Makefile
libjpeg/src/libjpeg/boxes/alphabox.cpp
libjpeg/src/libjpeg/boxes/alphabox.hpp
libjpeg/src/libjpeg/boxes/box.cpp
libjpeg/src/libjpeg/boxes/box.hpp
libjpeg/src/libjpeg/boxes/checksumbox.cpp
libjpeg/src/libjpeg/boxes/checksumbox.hpp
libjpeg/src/libjpeg/boxes/colortrafobox.cpp
libjpeg/src/libjpeg/boxes/colortrafobox.hpp
libjpeg/src/libjpeg/boxes/databox.cpp
libjpeg/src/libjpeg/boxes/databox.hpp
libjpeg/src/libjpeg/boxes/dctbox.cpp
libjpeg/src/libjpeg/boxes/dctbox.hpp
libjpeg/src/libjpeg/boxes/filetypebox.cpp
libjpeg/src/libjpeg/boxes/filetypebox.hpp
libjpeg/src/libjpeg/boxes/floattonemappingbox.cpp
libjpeg/src/libjpeg/boxes/floattonemappingbox.hpp
libjpeg/src/libjpeg/boxes/floattransformationbox.cpp
libjpeg/src/libjpeg/boxes/floattransformationbox.hpp
libjpeg/src/libjpeg/boxes/inversetonemappingbox.cpp
libjpeg/src/libjpeg/boxes/inversetonemappingbox.hpp
libjpeg/src/libjpeg/boxes/lineartransformationbox.cpp
pymedphys_pylibjpeg_libjpeg-1.3.1.dist-info/LICENSE
pymedphys_pylibjpeg_libjpeg-1.3.1.dist-info/METADATA
pymedphys_pylibjpeg_libjpeg-1.3.1.dist-info/WHEEL
pymedphys_pylibjpeg_libjpeg-1.3.1.dist-info/entry_points.txt
pymedphys_pylibjpeg_libjpeg-1.3.1.dist-info/top_level.txt
pymedphys_pylibjpeg_libjpeg-1.3.1.dist-info/RECORD
