Metadata-Version: 2.1
Name: pymedphys-pylibjpeg-libjpeg
Version: 1.3.1
Summary: A Python wrapper for libjpeg, with a focus on use as a plugin for for pylibjpeg
Home-page: https://github.com/pydicom/pylibjpeg-libjpeg
Author: scaramallion
Author-email: scaramallion@users.noreply.github.com
License: GPL V3.0
Keywords: dicom pydicom python jpg jpeg jpg-ls jpeg-ls libjpeg pylibjpeg
Platform: UNKNOWN
Classifier: License :: OSI Approved :: GNU General Public License v3 (GPLv3)
Classifier: Intended Audience :: Developers
Classifier: Intended Audience :: Healthcare Industry
Classifier: Intended Audience :: Science/Research
Classifier: Development Status :: 5 - Production/Stable
Classifier: Natural Language :: English
Classifier: Programming Language :: C++
Classifier: Programming Language :: Python :: 3.7
Classifier: Programming Language :: Python :: 3.8
Classifier: Programming Language :: Python :: 3.9
Classifier: Programming Language :: Python :: 3.10
Classifier: Operating System :: MacOS :: MacOS X
Classifier: Operating System :: POSIX :: Linux
Classifier: Operating System :: Microsoft :: Windows
Classifier: Topic :: Scientific/Engineering :: Medical Science Apps.
Classifier: Topic :: Software Development :: Libraries
Requires-Python: >=3.7
License-File: LICENSE
Requires-Dist: numpy (>=1.20) ; python_version == "3.7"
Requires-Dist: numpy (>=1.22) ; python_version >= "3.8"
